{
 "cells": [
  {
   "cell_type": "markdown",
   "metadata": {},
   "source": [
    "# Байткод"
   ]
  },
  {
   "cell_type": "code",
   "execution_count": 1,
   "metadata": {},
   "outputs": [],
   "source": [
    "def example_function():\n",
    "    print('Example function')"
   ]
  },
  {
   "cell_type": "markdown",
   "metadata": {},
   "source": [
    "У функций, есть атрибут `__code__`, например у объявленной нами ранее функции `example_function`:"
   ]
  },
  {
   "cell_type": "code",
   "execution_count": 2,
   "metadata": {},
   "outputs": [
    {
     "name": "stdout",
     "output_type": "stream",
     "text": [
      "['__annotations__', '__call__', '__class__', '__closure__', '__code__', '__defaults__', '__delattr__', '__dict__', '__dir__', '__doc__', '__eq__', '__format__', '__ge__', '__get__', '__getattribute__', '__globals__', '__gt__', '__hash__', '__init__', '__init_subclass__', '__kwdefaults__', '__le__', '__lt__', '__module__', '__name__', '__ne__', '__new__', '__qualname__', '__reduce__', '__reduce_ex__', '__repr__', '__setattr__', '__sizeof__', '__str__', '__subclasshook__']\n"
     ]
    }
   ],
   "source": [
    "print(dir(example_function))"
   ]
  },
  {
   "cell_type": "markdown",
   "metadata": {},
   "source": [
    "Атрибут `__code__` возвращает объект, который оборачивает исходный код, который вы пишите:"
   ]
  },
  {
   "cell_type": "code",
   "execution_count": 3,
   "metadata": {},
   "outputs": [
    {
     "name": "stdout",
     "output_type": "stream",
     "text": [
      "<code object example_function at 0x7f4dd0e15f60, file \"<ipython-input-1-85f25283a89c>\", line 1>\n"
     ]
    }
   ],
   "source": [
    "print(example_function.__code__)"
   ]
  },
  {
   "cell_type": "markdown",
   "metadata": {},
   "source": [
    "У этого объекта есть свой атрибут `co_code`, который возвращает байтовую строку, которая содержит инструкцию одну за другой функции `example_function`. Это байт-код, который Python сгенерировал для этой функции, и этот тот код котрый будет исполнятся интерпретатором Python:"
   ]
  },
  {
   "cell_type": "code",
   "execution_count": 4,
   "metadata": {},
   "outputs": [
    {
     "name": "stdout",
     "output_type": "stream",
     "text": [
      "b't\\x00d\\x01\\x83\\x01\\x01\\x00d\\x00S\\x00'\n"
     ]
    }
   ],
   "source": [
    "print(example_function.__code__.co_code)"
   ]
  },
  {
   "cell_type": "markdown",
   "metadata": {},
   "source": [
    "Эту байтовую строку, можно дезассемблировать в человекочитаемый код с помощью модуля `dis`:"
   ]
  },
  {
   "cell_type": "code",
   "execution_count": 5,
   "metadata": {},
   "outputs": [
    {
     "name": "stdout",
     "output_type": "stream",
     "text": [
      "  2           0 LOAD_GLOBAL              0 (print)\n",
      "              2 LOAD_CONST               1 ('Example function')\n",
      "              4 CALL_FUNCTION            1\n",
      "              6 POP_TOP\n",
      "              8 LOAD_CONST               0 (None)\n",
      "             10 RETURN_VALUE\n",
      "None\n"
     ]
    }
   ],
   "source": [
    "import dis\n",
    "print(dis.dis(example_function))"
   ]
  },
  {
   "cell_type": "markdown",
   "metadata": {},
   "source": [
    "Инструкций существует большое количество, посмотреть их можно с помощью модуля `opcode`:"
   ]
  },
  {
   "cell_type": "code",
   "execution_count": 6,
   "metadata": {},
   "outputs": [
    {
     "name": "stdout",
     "output_type": "stream",
     "text": [
      "{'POP_TOP': 1, 'ROT_TWO': 2, 'ROT_THREE': 3, 'DUP_TOP': 4, 'DUP_TOP_TWO': 5, 'NOP': 9, 'UNARY_POSITIVE': 10, 'UNARY_NEGATIVE': 11, 'UNARY_NOT': 12, 'UNARY_INVERT': 15, 'BINARY_MATRIX_MULTIPLY': 16, 'INPLACE_MATRIX_MULTIPLY': 17, 'BINARY_POWER': 19, 'BINARY_MULTIPLY': 20, 'BINARY_MODULO': 22, 'BINARY_ADD': 23, 'BINARY_SUBTRACT': 24, 'BINARY_SUBSCR': 25, 'BINARY_FLOOR_DIVIDE': 26, 'BINARY_TRUE_DIVIDE': 27, 'INPLACE_FLOOR_DIVIDE': 28, 'INPLACE_TRUE_DIVIDE': 29, 'GET_AITER': 50, 'GET_ANEXT': 51, 'BEFORE_ASYNC_WITH': 52, 'INPLACE_ADD': 55, 'INPLACE_SUBTRACT': 56, 'INPLACE_MULTIPLY': 57, 'INPLACE_MODULO': 59, 'STORE_SUBSCR': 60, 'DELETE_SUBSCR': 61, 'BINARY_LSHIFT': 62, 'BINARY_RSHIFT': 63, 'BINARY_AND': 64, 'BINARY_XOR': 65, 'BINARY_OR': 66, 'INPLACE_POWER': 67, 'GET_ITER': 68, 'GET_YIELD_FROM_ITER': 69, 'PRINT_EXPR': 70, 'LOAD_BUILD_CLASS': 71, 'YIELD_FROM': 72, 'GET_AWAITABLE': 73, 'INPLACE_LSHIFT': 75, 'INPLACE_RSHIFT': 76, 'INPLACE_AND': 77, 'INPLACE_XOR': 78, 'INPLACE_OR': 79, 'BREAK_LOOP': 80, 'WITH_CLEANUP_START': 81, 'WITH_CLEANUP_FINISH': 82, 'RETURN_VALUE': 83, 'IMPORT_STAR': 84, 'SETUP_ANNOTATIONS': 85, 'YIELD_VALUE': 86, 'POP_BLOCK': 87, 'END_FINALLY': 88, 'POP_EXCEPT': 89, 'STORE_NAME': 90, 'DELETE_NAME': 91, 'UNPACK_SEQUENCE': 92, 'FOR_ITER': 93, 'UNPACK_EX': 94, 'STORE_ATTR': 95, 'DELETE_ATTR': 96, 'STORE_GLOBAL': 97, 'DELETE_GLOBAL': 98, 'LOAD_CONST': 100, 'LOAD_NAME': 101, 'BUILD_TUPLE': 102, 'BUILD_LIST': 103, 'BUILD_SET': 104, 'BUILD_MAP': 105, 'LOAD_ATTR': 106, 'COMPARE_OP': 107, 'IMPORT_NAME': 108, 'IMPORT_FROM': 109, 'JUMP_FORWARD': 110, 'JUMP_IF_FALSE_OR_POP': 111, 'JUMP_IF_TRUE_OR_POP': 112, 'JUMP_ABSOLUTE': 113, 'POP_JUMP_IF_FALSE': 114, 'POP_JUMP_IF_TRUE': 115, 'LOAD_GLOBAL': 116, 'CONTINUE_LOOP': 119, 'SETUP_LOOP': 120, 'SETUP_EXCEPT': 121, 'SETUP_FINALLY': 122, 'LOAD_FAST': 124, 'STORE_FAST': 125, 'DELETE_FAST': 126, 'STORE_ANNOTATION': 127, 'RAISE_VARARGS': 130, 'CALL_FUNCTION': 131, 'MAKE_FUNCTION': 132, 'BUILD_SLICE': 133, 'LOAD_CLOSURE': 135, 'LOAD_DEREF': 136, 'STORE_DEREF': 137, 'DELETE_DEREF': 138, 'CALL_FUNCTION_KW': 141, 'CALL_FUNCTION_EX': 142, 'SETUP_WITH': 143, 'LIST_APPEND': 145, 'SET_ADD': 146, 'MAP_ADD': 147, 'LOAD_CLASSDEREF': 148, 'EXTENDED_ARG': 144, 'BUILD_LIST_UNPACK': 149, 'BUILD_MAP_UNPACK': 150, 'BUILD_MAP_UNPACK_WITH_CALL': 151, 'BUILD_TUPLE_UNPACK': 152, 'BUILD_SET_UNPACK': 153, 'SETUP_ASYNC_WITH': 154, 'FORMAT_VALUE': 155, 'BUILD_CONST_KEY_MAP': 156, 'BUILD_STRING': 157, 'BUILD_TUPLE_UNPACK_WITH_CALL': 158}\n"
     ]
    }
   ],
   "source": [
    "import opcode\n",
    "print(opcode.opmap)"
   ]
  }
 ],
 "metadata": {
  "kernelspec": {
   "display_name": "Python 3",
   "language": "python",
   "name": "python3"
  },
  "language_info": {
   "codemirror_mode": {
    "name": "ipython",
    "version": 3
   },
   "file_extension": ".py",
   "mimetype": "text/x-python",
   "name": "python",
   "nbconvert_exporter": "python",
   "pygments_lexer": "ipython3",
   "version": "3.6.3"
  }
 },
 "nbformat": 4,
 "nbformat_minor": 2
}
